relatives/__init__.py
relatives/model_admin.py
relatives/static/css/relatives.css
relatives/template_helpers.py
relatives/templates/relatives/change_form.html
relatives/templates/relatives/includes/fieldset.html
relatives/templatetags/__init__.py
relatives/templatetags/relatives.py
relatives/tests/__init__.py
relatives/tests/admin.py
relatives/tests/migrations/0001_initial.py
relatives/tests/migrations/0002_shape.py
relatives/tests/migrations/0003_auto_20210927_1618.py
relatives/tests/migrations/0004_eater_meal.py
relatives/tests/migrations/__init__.py
relatives/tests/models.py
relatives/tests/templates/admin/includes/fieldset.html
relatives/tests/templates/related_objects_fk_test.html
relatives/tests/templates/related_objects_generic_test.html
relatives/tests/templates/related_objects_m2m_test.html
relatives/tests/tests.py
relatives/tests/urls.py
relatives/utils.py
django_relatives-1.3.0.dist-info/WHEEL
django_relatives-1.3.0.dist-info/METADATA
django_relatives-1.3.0.dist-info/licenses/LICENSE
django_relatives-1.3.0.dist-info/licenses/AUTHORS.rst
django_relatives-1.3.0.dist-info/RECORD
