Metadata-Version: 2.1
Name: django-relatives
Version: 1.3.0
Summary: Utilities for linking to related objects in Django admin
License: MIT
Author-email: Trey Hunner <trey@treyhunner.com>
Requires-Python: >=3.8
Classifier: Development Status :: 5 - Production/Stable
Classifier: Environment :: Web Environment
Classifier: Framework :: Django
Classifier: Framework :: Django :: 3.2
Classifier: Framework :: Django :: 4.1
Classifier: Framework :: Django :: 4.2
Classifier: Intended Audience :: Developers
Classifier: License :: OSI Approved :: MIT License
Classifier: Operating System :: OS Independent
Classifier: Programming Language :: Python
Classifier: Programming Language :: Python :: 3
Classifier: Programming Language :: Python :: 3.8
Classifier: Programming Language :: Python :: 3.9
Requires-Dist: Django>=3.2
Project-URL: changelog, https://github.com/treyhunner/django-relatives/blob/main/CHANGES.rst
Project-URL: documentation, https://django-relatives.readthedocs.io
Project-URL: issue-tracker, https://github.com/treyhunner/django-relatives/issues
Project-URL: repository, https://github.com/treyhunner/django-relatives
